pyskoptimize/__init__.py
pyskoptimize/base.py
pyskoptimize/params.py
pyskoptimize/steps.py
pyskoptimize/traits.py
pyskoptimize-1.0.0.dist-info/WHEEL
pyskoptimize-1.0.0.dist-info/METADATA
pyskoptimize-1.0.0.dist-info/RECORD
